napari_figure/__init__.py
napari_figure/_version.py
napari_figure/figure_widget.py
napari_figure/napari.yaml
napari_figure/_tests/__init__.py
napari_figure/_tests/test_widget.py
napari_figure-0.1.1.dist-info/LICENSE
napari_figure-0.1.1.dist-info/METADATA
napari_figure-0.1.1.dist-info/WHEEL
napari_figure-0.1.1.dist-info/entry_points.txt
napari_figure-0.1.1.dist-info/top_level.txt
napari_figure-0.1.1.dist-info/RECORD
